my_uploader/app.py
myoutube/app.py
my_uploader-0.0.1.dist-info/METADATA
my_uploader-0.0.1.dist-info/WHEEL
my_uploader-0.0.1.dist-info/top_level.txt
my_uploader-0.0.1.dist-info/RECORD
