Metadata-Version: 2.1
Name: my_uploader
Version: 0.0.1
Summary: my youtube algorithm analist
Author: Jagari
